FreeBack/__init__.py
FreeBack/alpha.py
FreeBack/barbybar.py
FreeBack/debug.py
FreeBack/display.py
FreeBack/event.py
FreeBack/my_pd.py
FreeBack/opt.py
FreeBack/post.py
FreeBack/signal.py
FreeBack/strat.py
FreeBack-6.3.1.dist-info/LICENSE
FreeBack-6.3.1.dist-info/METADATA
FreeBack-6.3.1.dist-info/WHEEL
FreeBack-6.3.1.dist-info/top_level.txt
FreeBack-6.3.1.dist-info/RECORD
