Metadata-Version: 2.1
Name: FreeBack
Version: 6.3.1
Summary: Package for backtest
Home-page: https://github.com/LHanLi/FreeBack
Author: LH.Li,zzq
Author-email: lh98lee@zju.edu.cn
Classifier: Programming Language :: Python :: 3
Classifier: License :: OSI Approved :: GNU General Public License v3 or later (GPLv3+)
Classifier: Operating System :: OS Independent
License-File: LICENSE
